liev/__init__.py
liev/liev.py
liev-0.1.3.dist-info/licenses/LICENSE.TXT
liev-0.1.3.dist-info/METADATA
liev-0.1.3.dist-info/WHEEL
liev-0.1.3.dist-info/top_level.txt
liev-0.1.3.dist-info/RECORD
