Metadata-Version: 2.4
Name: liev
Version: 0.1.3
Summary: Liev LLM Dispatcher client
Home-page: https://liev.ai
Author: Liev.ai
Author-email: gabriel.penna@inmetrics.com.br
Classifier: Programming Language :: Python :: 3
Classifier: Operating System :: OS Independent
Requires-Python: >=3.9
License-File: LICENSE.TXT
Requires-Dist: requests>=2.32.4
Requires-Dist: openai>=1.92.0
Dynamic: author
Dynamic: author-email
Dynamic: classifier
Dynamic: description
Dynamic: description-content-type
Dynamic: home-page
Dynamic: license-file
Dynamic: requires-dist
Dynamic: requires-python
Dynamic: summary
